vasyok/__init__.py
vasyok/main_program.py
vasyok-0.1.0.dist-info/WHEEL
vasyok-0.1.0.dist-info/METADATA
vasyok-0.1.0.dist-info/RECORD
